rst2md.py
rst2md-0.1.1.dist-info/WHEEL
rst2md-0.1.1.dist-info/METADATA
rst2md-0.1.1.dist-info/RECORD
